fava_review/__init__.py
fava_review/pivot_review.py
fava_review/templates/FavaReview.html
fava_review/templates/__init__.py
fava_review-1.0.1.dist-info/LICENSE
fava_review-1.0.1.dist-info/METADATA
fava_review-1.0.1.dist-info/WHEEL
fava_review-1.0.1.dist-info/RECORD
