Metadata-Version: 2.1
Name: fava-review
Version: 1.0.1
Summary: A Fava extension to help review transactions over a series of periods.
License: MIT
Author: Jakub Jamro
Author-email: kuba.jamro@gmail.com
Requires-Python: >=3.8,<4.0
Classifier: License :: OSI Approved :: MIT License
Classifier: Programming Language :: Python :: 3
Classifier: Programming Language :: Python :: 3.8
Classifier: Programming Language :: Python :: 3.9
Classifier: Programming Language :: Python :: 3.10
Classifier: Programming Language :: Python :: 3.11
Requires-Dist: beautifulsoup4 (>=4.10.0,<5.0.0)
Requires-Dist: fava (==1.25.1)
Requires-Dist: petl (>=1.7.4,<2.0.0)
